qserverinfo/entry.py
qserverinfo/local_run.py
qserverinfo/app/ArgsParser.py
qserverinfo/app/Config.py
qserverinfo/app/MainWindow.py
qserverinfo/app/TrayIcon.py
qserverinfo/app/TrayMenu.py
qserverinfo/app/__init__.py
qserverinfo/app/main.py
qserverinfo/app/data/Xolonium-Bold.ttf
qserverinfo/app/data/credits.md
qserverinfo/app/data/quake.png
qserverinfo/app/server/DummyServer.py
qserverinfo/app/server/PlayerData.py
qserverinfo/app/server/Server.py
qserverinfo/app/server/ServerData.py
qserverinfo/app/server/ServerText.py
qserverinfo/app/server/__init__.py
qserverinfo/app/styles/main.css
qserverinfo/app/text_parsers/PlainTextParser.py
qserverinfo/app/text_parsers/QuakeTextParser.py
qserverinfo/app/text_parsers/TextParserAbstract.py
qserverinfo/app/text_parsers/XonoticTextParser.py
qserverinfo/app/text_parsers/__init__.py
qserverinfo/app/utils/__init__.py
qserverinfo/app/utils/color_processing.py
qserverinfo/app/utils/gtk.py
qserverinfo/app/utils/image_manipulation.py
qserverinfo/app/widgets/ExBox.py
qserverinfo/app/widgets/ExLabel.py
qserverinfo/app/widgets/PlayersTable.py
qserverinfo/app/widgets/ServerDetailsWidget.py
qserverinfo/app/widgets/WidgetExtensions.py
qserverinfo/app/widgets/__init__.py
qserverinfo-1.0.5.dist-info/LICENSE
qserverinfo-1.0.5.dist-info/METADATA
qserverinfo-1.0.5.dist-info/WHEEL
qserverinfo-1.0.5.dist-info/entry_points.txt
qserverinfo-1.0.5.dist-info/top_level.txt
qserverinfo-1.0.5.dist-info/RECORD
