Metadata-Version: 2.1
Name: qserverinfo
Version: 1.0.5
Summary: Shows info about quake servers in the tray
Author: ColdSpirit
License: GNU AFFERO GENERAL PUBLIC LICENSE
Project-URL: Homepage, https://github.com/ColdSpirit0/QServerInfo
Project-URL: Bug Tracker, https://github.com/ColdSpirit0/QServerInfo/issues
Keywords: quake,tray,server,info,xonotic,doombringer
Classifier: License :: OSI Approved :: GNU Affero General Public License v3
Classifier: Programming Language :: Python
Classifier: Programming Language :: Python :: 3
Requires-Python: >=3.10
License-File: LICENSE
Requires-Dist: colour (==0.1.5)
Requires-Dist: Pillow (==9.3.0)
Requires-Dist: PyGObject (==3.42.2)
Requires-Dist: pyq3serverlist (==0.2.0)
